pykka/__init__.py
pykka/_actor.py
pykka/_envelope.py
pykka/_exceptions.py
pykka/_future.py
pykka/_introspection.py
pykka/_proxy.py
pykka/_ref.py
pykka/_registry.py
pykka/_threading.py
pykka/_types.py
pykka/debug.py
pykka/messages.py
pykka/py.typed
pykka/typing.py
pykka-4.4.1.dist-info/METADATA
pykka-4.4.1.dist-info/WHEEL
pykka-4.4.1.dist-info/licenses/LICENSE
pykka-4.4.1.dist-info/RECORD
