Metadata-Version: 2.4
Name: pykka
Version: 4.4.1
Summary: Pykka is a Python implementation of the actor model
Project-URL: Source code, https://github.com/jodal/pykka
Project-URL: Documentation, https://pykka.readthedocs.io/
Author-email: Stein Magnus Jodal <stein.magnus@jodal.no>
License-Expression: Apache-2.0
License-File: LICENSE
Keywords: actor,concurrency,threading
Classifier: Development Status :: 5 - Production/Stable
Classifier: Intended Audience :: Developers
Classifier: Topic :: Software Development :: Libraries
Requires-Python: >=3.10
